prettytable/__init__.py
prettytable/__main__.py
prettytable/_version.py
prettytable/colortable.py
prettytable/prettytable.py
prettytable/py.typed
prettytable-3.15.0.dist-info/METADATA
prettytable-3.15.0.dist-info/WHEEL
prettytable-3.15.0.dist-info/licenses/LICENSE
prettytable-3.15.0.dist-info/RECORD
