Metadata-Version: 2.4
Name: prettytable
Version: 3.15.0
Summary: A simple Python library for easily displaying tabular data in a visually appealing ASCII table format
Project-URL: Changelog, https://github.com/prettytable/prettytable/releases
Project-URL: Funding, https://tidelift.com/subscription/pkg/pypi-prettytable?utm_source=pypi-prettytable&utm_medium=pypi
Project-URL: Homepage, https://github.com/prettytable/prettytable
Project-URL: Source, https://github.com/prettytable/prettytable
Author-email: Luke Maurits <luke@maurits.id.au>
Maintainer: Hugo van Kemenade
License-Expression: BSD-3-Clause
License-File: LICENSE
Classifier: Programming Language :: Python
Classifier: Programming Language :: Python :: 3 :: Only
Classifier: Programming Language :: Python :: 3.9
Classifier: Programming Language :: Python :: 3.10
Classifier: Programming Language :: Python :: 3.11
Classifier: Programming Language :: Python :: 3.12
Classifier: Programming Language :: Python :: 3.13
Classifier: Programming Language :: Python :: 3.14
Classifier: Programming Language :: Python :: Implementation :: CPython
Classifier: Programming Language :: Python :: Implementation :: PyPy
Classifier: Topic :: Text Processing
Classifier: Typing :: Typed
Requires-Python: >=3.9
Requires-Dist: wcwidth
Provides-Extra: tests
Requires-Dist: pytest; extra == 'tests'
Requires-Dist: pytest-cov; extra == 'tests'
Requires-Dist: pytest-lazy-fixtures; extra == 'tests'
